ansq/__init__.py
ansq/py.typed
ansq/typedefs.py
ansq/utils.py
ansq/http/__init__.py
ansq/http/base.py
ansq/http/http_exceptions.py
ansq/http/lookupd.py
ansq/http/writer.py
ansq/tcp/__init__.py
ansq/tcp/connection.py
ansq/tcp/consts.py
ansq/tcp/exceptions.py
ansq/tcp/protocol.py
ansq/tcp/reader.py
ansq/tcp/writer.py
ansq/tcp/types/__init__.py
ansq/tcp/types/client.py
ansq/tcp/types/commands.py
ansq/tcp/types/connection.py
ansq/tcp/types/connection_status.py
ansq/tcp/types/frame_type.py
ansq/tcp/types/message.py
ansq/tcp/types/response_schemas.py
ansq-0.3.0.dist-info/LICENSE
ansq-0.3.0.dist-info/METADATA
ansq-0.3.0.dist-info/WHEEL
ansq-0.3.0.dist-info/top_level.txt
ansq-0.3.0.dist-info/RECORD
